README.md
setup.py
idac_sdk/__init__.py
idac_sdk/_version.py
idac_sdk/errors.py
idac_sdk/log.py
idac_sdk/session_data.py
idac_sdk/types.py
idac_sdk.egg-info/PKG-INFO
idac_sdk.egg-info/SOURCES.txt
idac_sdk.egg-info/dependency_links.txt
idac_sdk.egg-info/entry_points.txt
idac_sdk.egg-info/requires.txt
idac_sdk.egg-info/top_level.txt
idac_sdk/asynced/__init__.py
idac_sdk/asynced/controller.py
idac_sdk/asynced/request.py
idac_sdk/base/__init__.py
idac_sdk/base/controller.py
idac_sdk/base/request.py
idac_sdk/cli/__init__.py
idac_sdk/cli/idac.py
idac_sdk/cli/commands/__init__.py
idac_sdk/cli/commands/cleanup.py
idac_sdk/cli/commands/config.py
idac_sdk/cli/commands/create.py
idac_sdk/cli/commands/extend.py
idac_sdk/cli/commands/restart.py
idac_sdk/cli/commands/status.py
idac_sdk/cli/lib/__init__.py
idac_sdk/cli/lib/_controller_options.py
idac_sdk/cli/lib/_helpers.py
idac_sdk/cli/lib/_vpn_options.py
idac_sdk/config/__init__.py
idac_sdk/lib/__init__.py
idac_sdk/lib/_helpers.py
idac_sdk/models/__init__.py
idac_sdk/models/auth.py
idac_sdk/models/config.py
idac_sdk/models/new_request.py
idac_sdk/models/request_state.py
idac_sdk/models/vpn_config.py
idac_sdk/synced/__init__.py
idac_sdk/synced/controller.py
idac_sdk/synced/request.py
tests/test_async.py
tests/test_sync.py