Metadata-Version: 2.1
Name: idac-sdk
Version: 0.7.4
Summary: Python 3 SDK for iDAC
Home-page: https://www-github.cisco.com/GDE-Content-Engineering/idac-sdk-python
Author: Cisco GDE CAT
Author-email: cat-dev-support@cisco.com
License: MIT
Keywords: idac sdk
Platform: UNKNOWN
Classifier: Development Status :: 4 - Beta
Classifier: Topic :: Software Development :: Libraries
Classifier: Topic :: Software Development :: Libraries :: Python Modules
Classifier: License :: OSI Approved :: MIT License
Classifier: Programming Language :: Python :: 3
Classifier: Programming Language :: Python :: 3.10
Classifier: Programming Language :: Python :: 3.11
Classifier: Programming Language :: Python :: 3.12
Requires-Python: >=3.10
